HttpPy/Arguments.py
HttpPy/ParseRequest.py
HttpPy/Request.py
HttpPy/__init__.py
HttpPy/__main__.py
HttpPy/Exceptions/KeyValDefinition.py
HttpPy/Exceptions/RequestDefinition.py
HttpPy/Exceptions/__init__.py
HttpPy/Logger/__init__.py
HttpPy/Logger/generics.py
HttpPy/Logger/request.py
HttpPy/decorators/__init__.py
HttpPy/decorators/timming.py
HttpPy-0.0.7.dist-info/LICENSE.md
HttpPy-0.0.7.dist-info/METADATA
HttpPy-0.0.7.dist-info/WHEEL
HttpPy-0.0.7.dist-info/entry_points.txt
HttpPy-0.0.7.dist-info/top_level.txt
HttpPy-0.0.7.dist-info/RECORD
