Metadata-Version: 2.1
Name: HttpPy
Version: 0.0.7
Summary: More comfortable requests with python
Home-page: https://github.com/everitosan/HttpClient/
Author: everitosan
Author-email: eve.san.dev@gmail.com
License: MIT
Platform: UNKNOWN
Classifier: License :: OSI Approved :: MIT License
Classifier: Programming Language :: Python :: 3
Classifier: Programming Language :: Python :: 3.6
Requires-Dist: colorama
Requires-Dist: requests
